plib/auth/__init__.py
plib/auth/encrypt.py
plib/auth/jwt.py
plib/auth/o2auth.py
plib/licensing/__init__.py
plib/licensing/api.py
plib/licensing/exceptions.py
plib/licensing/models.py
plib/tracing/__init__.py
plib/tracing/utils.py
platform_library-0.4.0.dist-info/LICENSE
platform_library-0.4.0.dist-info/METADATA
platform_library-0.4.0.dist-info/WHEEL
platform_library-0.4.0.dist-info/top_level.txt
platform_library-0.4.0.dist-info/RECORD
