Metadata-Version: 2.1
Name: platform-library
Version: 0.4.0
Summary: A library for easy developing Platform
Author: Artyom Vakilov
License: MIT License
Classifier: Programming Language :: Python :: 3
Classifier: License :: OSI Approved :: MIT License
Classifier: Operating System :: OS Independent
Requires-Python: >=3.8
License-File: LICENSE
Requires-Dist: PyJWT (==2.8.0)
Requires-Dist: requests (==2.31.0)
Requires-Dist: opentelemetry-exporter-otlp (==1.19.0)
